.keep
marrow/package/__init__.py
marrow/package/cache.py
marrow/package/canonical.py
marrow/package/disport.py
marrow/package/host.py
marrow/package/lazy.py
marrow/package/loader.py
marrow/package/py.typed
marrow/package/release.py
marrow/package/tarjan.py
marrow/package/__pycache__/__init__.cpython-311.opt-1.pyc
marrow/package/__pycache__/cache.cpython-311.opt-1.pyc
marrow/package/__pycache__/canonical.cpython-311.opt-1.pyc
marrow/package/__pycache__/disport.cpython-311.opt-1.pyc
marrow/package/__pycache__/host.cpython-311.opt-1.pyc
marrow/package/__pycache__/lazy.cpython-311.opt-1.pyc
marrow/package/__pycache__/loader.cpython-311.opt-1.pyc
marrow/package/__pycache__/release.cpython-311.opt-1.pyc
marrow/package/__pycache__/tarjan.cpython-311.opt-1.pyc
marrow.package-2.1.1.dist-info/LICENSE.txt
marrow.package-2.1.1.dist-info/METADATA
marrow.package-2.1.1.dist-info/WHEEL
marrow.package-2.1.1.dist-info/entry_points.txt
marrow.package-2.1.1.dist-info/top_level.txt
marrow.package-2.1.1.dist-info/RECORD
